<!--

    Copyright (c) 2019 TerraFrame, Inc. All rights reserved.

    This file is part of Geoprism Registry(tm).

    Geoprism Registry(tm) is free software: you can redistribute it and/or modify
    it under the terms of the GNU Lesser General Public License as
    published by the Free Software Foundation, either version 3 of the
    License, or (at your option) any later version.

    Geoprism Registry(tm) is distributed in the hope that it will be useful, but
    WITHOUT ANY WARRANTY; without even the implied warranty of
    MERCHANTABILITY or FITNESS FOR A PARTICULAR PURPOSE.  See the
    GNU Lesser General Public License for more details.

    You should have received a copy of the GNU Lesser General Public
    License along with Geoprism Registry(tm).  If not, see <http://www.gnu.org/licenses/>.

-->
<version xsi:noNamespaceSchemaLocation="classpath:com/runwaysdk/resources/xsd/version.xsd" xmlns:xsi="http://www.w3.org/2001/XMLSchema-instance">
  <doIt>
  
       <createOrUpdate>
       
       	  <object type="com.runwaysdk.localization.LocalizedValueStore" key="scheduledjobs.title">
	        <attribute name="storeTag" value="UIText" />
	        <attribute name="storeKey" value="scheduledjobs.title" />
	        <attributeStruct name="storeValue">
	          <attribute name="defaultLocale" value="Scheduled Jobs" />
	        </attributeStruct>
	      </object>
	      
	      <object type="com.runwaysdk.localization.LocalizedValueStore" key="scheduledjobs.details.title">
	        <attribute name="storeTag" value="UIText" />
	        <attribute name="storeKey" value="scheduledjobs.details.title" />
	        <attributeStruct name="storeValue">
	          <attribute name="defaultLocale" value="Job Details" />
	        </attributeStruct>
	      </object>

	      <object type="com.runwaysdk.localization.LocalizedValueStore" key="scheduledjobs.jobs.table.header">
	        <attribute name="storeTag" value="UIText" />
	        <attribute name="storeKey" value="scheduledjobs.jobs.table.header" />
	        <attributeStruct name="storeValue">
	          <attribute name="defaultLocale" value="In progress" />
	        </attributeStruct>
	      </object>
	      
	      <object type="com.runwaysdk.localization.LocalizedValueStore" key="scheduledjobs.completedjobs.table.header">
	        <attribute name="storeTag" value="UIText" />
	        <attribute name="storeKey" value="scheduledjobs.completedjobs.table.header" />
	        <attributeStruct name="storeValue">
	          <attribute name="defaultLocale" value="Completed Jobs" />
	        </attributeStruct>
	      </object>
	      
	      <object type="com.runwaysdk.localization.LocalizedValueStore" key="scheduledjobs.detail.button">
	        <attribute name="storeTag" value="UIText" />
	        <attribute name="storeKey" value="scheduledjobs.detail.button" />
	        <attributeStruct name="storeValue">
	          <attribute name="defaultLocale" value="Details" />
	        </attributeStruct>
	      </object>
	      
	      <object type="com.runwaysdk.localization.LocalizedValueStore" key="scheduledjobs.view.completed.jobs.button">
	        <attribute name="storeTag" value="UIText" />
	        <attribute name="storeKey" value="scheduledjobs.view.completed.jobs.button" />
	        <attributeStruct name="storeValue">
	          <attribute name="defaultLocale" value="View completed jobs" />
	        </attributeStruct>
	      </object>
	      
	      <object type="com.runwaysdk.localization.LocalizedValueStore" key="scheduledjobs.view.more.button">
	        <attribute name="storeTag" value="UIText" />
	        <attribute name="storeKey" value="scheduledjobs.view.more.button" />
	        <attributeStruct name="storeValue">
	          <attribute name="defaultLocale" value="View all" />
	        </attributeStruct>
	      </object>
	      
	      <object type="com.runwaysdk.localization.LocalizedValueStore" key="scheduledjobs.problemdetail.modal.title">
	        <attribute name="storeTag" value="UIText" />
	        <attribute name="storeKey" value="scheduledjobs.problemdetail.modal.title" />
	        <attributeStruct name="storeValue">
	          <attribute name="defaultLocale" value="Problem Resolution" />
	        </attributeStruct>
	      </object>
	      
	      <object type="com.runwaysdk.localization.LocalizedValueStore" key="scheduledjobs.menu">
	        <attribute name="storeTag" value="UIText" />
	        <attribute name="storeKey" value="scheduledjobs.menu" />
	        <attributeStruct name="storeValue">
	          <attribute name="defaultLocale" value="Scheduled Jobs" />
	        </attributeStruct>
	      </object>
	      
      </createOrUpdate>
      
    <create></create>
    <update></update>
  </doIt>
  <undoIt>
    <delete></delete>
  </undoIt>
</version>